{
  "id": "550e8400-e29b-41d4-a716-446655440013",
  "name": "Corner Weave",
  "description": "Bends collect in the corners and open only after careful clears.",
  "difficulty": "EASY",
  "order": 4,
  "attempts": 6,
  "arrows": [
    {
      "id": "a",
      "color": "blue",
      "path": [
        {
          "row": 7,
          "col": 9
        },
        {
          "row": 7,
          "col": 8
        },
        {
          "row": 7,
          "col": 7
        },
        {
          "row": 6,
          "col": 7
        },
        {
          "row": 5,
          "col": 7
        },
        {
          "row": 4,
          "col": 7
        }
      ],
      "direction": "LEFT"
    },
    {
      "id": "b",
      "color": "green",
      "path": [
        {
          "row": 5,
          "col": 1
        },
        {
          "row": 4,
          "col": 1
        },
        {
          "row": 4,
          "col": 0
        },
        {
          "row": 3,
          "col": 0
        },
        {
          "row": 2,
          "col": 0
        },
        {
          "row": 1,
          "col": 0
        }
      ],
      "direction": "UP"
    },
    {
      "id": "c",
      "color": "yellow",
      "path": [
        {
          "row": 8,
          "col": 6
        },
        {
          "row": 7,
          "col": 6
        },
        {
          "row": 6,
          "col": 6
        },
        {
          "row": 5,
          "col": 6
        },
        {
          "row": 4,
          "col": 6
        },
        {
          "row": 4,
          "col": 5
        }
      ],
      "direction": "LEFT"
    },
    {
      "id": "d",
      "color": "pink",
      "path": [
        {
          "row": 8,
          "col": 2
        },
        {
          "row": 7,
          "col": 2
        },
        {
          "row": 6,
          "col": 2
        },
        {
          "row": 5,
          "col": 2
        },
        {
          "row": 4,
          "col": 2
        },
        {
          "row": 3,
          "col": 2
        }
      ],
      "direction": "LEFT"
    },
    {
      "id": "e",
      "color": "cyan",
      "path": [
        {
          "row": 6,
          "col": 9
        },
        {
          "row": 5,
          "col": 9
        },
        {
          "row": 5,
          "col": 8
        }
      ],
      "direction": "LEFT"
    },
    {
      "id": "f",
      "color": "purple",
      "path": [
        {
          "row": 7,
          "col": 4
        },
        {
          "row": 7,
          "col": 3
        },
        {
          "row": 6,
          "col": 3
        },
        {
          "row": 5,
          "col": 3
        },
        {
          "row": 4,
          "col": 3
        },
        {
          "row": 3,
          "col": 3
        }
      ],
      "direction": "LEFT"
    },
    {
      "id": "g",
      "color": "crimson",
      "path": [
        {
          "row": 6,
          "col": 4
        },
        {
          "row": 5,
          "col": 4
        },
        {
          "row": 4,
          "col": 4
        },
        {
          "row": 3,
          "col": 4
        },
        {
          "row": 2,
          "col": 4
        },
        {
          "row": 1,
          "col": 4
        }
      ],
      "direction": "LEFT"
    },
    {
      "id": "h",
      "color": "white",
      "path": [
        {
          "row": 4,
          "col": 9
        },
        {
          "row": 3,
          "col": 9
        },
        {
          "row": 3,
          "col": 8
        }
      ],
      "direction": "LEFT"
    },
    {
      "id": "i",
      "color": "orange",
      "path": [
        {
          "row": 3,
          "col": 1
        },
        {
          "row": 2,
          "col": 1
        },
        {
          "row": 1,
          "col": 1
        },
        {
          "row": 0,
          "col": 1
        },
        {
          "row": 0,
          "col": 0
        }
      ],
      "direction": "UP"
    },
    {
      "id": "j",
      "color": "teal",
      "path": [
        {
          "row": 7,
          "col": 5
        },
        {
          "row": 6,
          "col": 5
        },
        {
          "row": 5,
          "col": 5
        }
      ],
      "direction": "LEFT"
    },
    {
      "id": "k",
      "color": "blue",
      "path": [
        {
          "row": 1,
          "col": 9
        },
        {
          "row": 1,
          "col": 8
        },
        {
          "row": 1,
          "col": 7
        },
        {
          "row": 1,
          "col": 6
        },
        {
          "row": 1,
          "col": 5
        }
      ],
      "direction": "LEFT"
    },
    {
      "id": "l",
      "color": "green",
      "path": [
        {
          "row": 8,
          "col": 1
        },
        {
          "row": 8,
          "col": 0
        },
        {
          "row": 7,
          "col": 0
        },
        {
          "row": 6,
          "col": 0
        },
        {
          "row": 5,
          "col": 0
        }
      ],
      "direction": "UP"
    },
    {
      "id": "m",
      "color": "yellow",
      "path": [
        {
          "row": 3,
          "col": 6
        },
        {
          "row": 3,
          "col": 5
        },
        {
          "row": 2,
          "col": 5
        }
      ],
      "direction": "LEFT"
    },
    {
      "id": "n",
      "color": "pink",
      "path": [
        {
          "row": 2,
          "col": 3
        },
        {
          "row": 1,
          "col": 3
        },
        {
          "row": 0,
          "col": 3
        },
        {
          "row": 0,
          "col": 2
        }
      ],
      "direction": "LEFT"
    },
    {
      "id": "o",
      "color": "cyan",
      "path": [
        {
          "row": 2,
          "col": 8
        },
        {
          "row": 2,
          "col": 7
        },
        {
          "row": 2,
          "col": 6
        }
      ],
      "direction": "LEFT"
    },
    {
      "id": "p",
      "color": "purple",
      "path": [
        {
          "row": 0,
          "col": 9
        },
        {
          "row": 0,
          "col": 8
        },
        {
          "row": 0,
          "col": 7
        },
        {
          "row": 0,
          "col": 6
        },
        {
          "row": 0,
          "col": 5
        },
        {
          "row": 0,
          "col": 4
        }
      ],
      "direction": "LEFT"
    },
    {
      "id": "q",
      "color": "crimson",
      "path": [
        {
          "row": 8,
          "col": 9
        },
        {
          "row": 8,
          "col": 8
        },
        {
          "row": 8,
          "col": 7
        }
      ],
      "direction": "UP"
    },
    {
      "id": "r",
      "color": "white",
      "path": [
        {
          "row": 8,
          "col": 5
        },
        {
          "row": 8,
          "col": 4
        },
        {
          "row": 8,
          "col": 3
        }
      ],
      "direction": "UP"
    }
  ]
}
